{
  "runner": "\u042f\u041d \u0421\u0435\u0440\u0433\u0456\u0439",
  "race": "IKS Ukraine",
  "year": 2021,
  "distance_id": "48h",
  "data_type": "laps",
  "source": "my.raceresult.com event 174509",
  "total_laps": 116,
  "total_time_sec": 86291.73,
  "laps": [
    {
      "lap": 1,
      "split_sec": 505.08,
      "cum_sec": 505.08
    },
    {
      "lap": 2,
      "split_sec": 489.71,
      "cum_sec": 994.79
    },
    {
      "lap": 3,
      "split_sec": 485.24,
      "cum_sec": 1480.02
    },
    {
      "lap": 4,
      "split_sec": 489.18,
      "cum_sec": 1969.2
    },
    {
      "lap": 5,
      "split_sec": 486.59,
      "cum_sec": 2455.79
    },
    {
      "lap": 6,
      "split_sec": 492.24,
      "cum_sec": 2948.03
    },
    {
      "lap": 7,
      "split_sec": 460.59,
      "cum_sec": 3408.61
    },
    {
      "lap": 8,
      "split_sec": 450.46,
      "cum_sec": 3859.07
    },
    {
      "lap": 9,
      "split_sec": 470.43,
      "cum_sec": 4329.49
    },
    {
      "lap": 10,
      "split_sec": 493.46,
      "cum_sec": 4822.94
    },
    {
      "lap": 11,
      "split_sec": 483.53,
      "cum_sec": 5306.46
    },
    {
      "lap": 12,
      "split_sec": 562.83,
      "cum_sec": 5869.29
    },
    {
      "lap": 13,
      "split_sec": 483.84,
      "cum_sec": 6353.12
    },
    {
      "lap": 14,
      "split_sec": 677.9,
      "cum_sec": 7031.02
    },
    {
      "lap": 15,
      "split_sec": 565.32,
      "cum_sec": 7596.33
    },
    {
      "lap": 16,
      "split_sec": 634.09,
      "cum_sec": 8230.42
    },
    {
      "lap": 17,
      "split_sec": 482.6,
      "cum_sec": 8713.02
    },
    {
      "lap": 18,
      "split_sec": 454.65,
      "cum_sec": 9167.67
    },
    {
      "lap": 19,
      "split_sec": 695.91,
      "cum_sec": 9863.57
    },
    {
      "lap": 20,
      "split_sec": 733.48,
      "cum_sec": 10597.05
    },
    {
      "lap": 21,
      "split_sec": 462.69,
      "cum_sec": 11059.73
    },
    {
      "lap": 22,
      "split_sec": 474.94,
      "cum_sec": 11534.67
    },
    {
      "lap": 23,
      "split_sec": 596.22,
      "cum_sec": 12130.88
    },
    {
      "lap": 24,
      "split_sec": 635.3,
      "cum_sec": 12766.18
    },
    {
      "lap": 25,
      "split_sec": 640.5,
      "cum_sec": 13406.68
    },
    {
      "lap": 26,
      "split_sec": 596.4,
      "cum_sec": 14003.08
    },
    {
      "lap": 27,
      "split_sec": 717.74,
      "cum_sec": 14720.81
    },
    {
      "lap": 28,
      "split_sec": 799.22,
      "cum_sec": 15520.02
    },
    {
      "lap": 29,
      "split_sec": 478.04,
      "cum_sec": 15998.06
    },
    {
      "lap": 30,
      "split_sec": 668.02,
      "cum_sec": 16666.08
    },
    {
      "lap": 31,
      "split_sec": 501.57,
      "cum_sec": 17167.65
    },
    {
      "lap": 32,
      "split_sec": 653.23,
      "cum_sec": 17820.88
    },
    {
      "lap": 33,
      "split_sec": 521.54,
      "cum_sec": 18342.41
    },
    {
      "lap": 34,
      "split_sec": 552.07,
      "cum_sec": 18894.47
    },
    {
      "lap": 35,
      "split_sec": 740.62,
      "cum_sec": 19635.08
    },
    {
      "lap": 36,
      "split_sec": 551.82,
      "cum_sec": 20186.9
    },
    {
      "lap": 37,
      "split_sec": 788.2,
      "cum_sec": 20975.1
    },
    {
      "lap": 38,
      "split_sec": 582.54,
      "cum_sec": 21557.63
    },
    {
      "lap": 39,
      "split_sec": 514.21,
      "cum_sec": 22071.84
    },
    {
      "lap": 40,
      "split_sec": 602.4,
      "cum_sec": 22674.24
    },
    {
      "lap": 41,
      "split_sec": 603.49,
      "cum_sec": 23277.72
    },
    {
      "lap": 42,
      "split_sec": 712.48,
      "cum_sec": 23990.19
    },
    {
      "lap": 43,
      "split_sec": 813.95,
      "cum_sec": 24804.14
    },
    {
      "lap": 44,
      "split_sec": 924.2,
      "cum_sec": 25728.33
    },
    {
      "lap": 45,
      "split_sec": 791.02,
      "cum_sec": 26519.35
    },
    {
      "lap": 46,
      "split_sec": 702.62,
      "cum_sec": 27221.97
    },
    {
      "lap": 47,
      "split_sec": 831.19,
      "cum_sec": 28053.15
    },
    {
      "lap": 48,
      "split_sec": 605.82,
      "cum_sec": 28658.97
    },
    {
      "lap": 49,
      "split_sec": 688.2,
      "cum_sec": 29347.17
    },
    {
      "lap": 50,
      "split_sec": 492.6,
      "cum_sec": 29839.77
    },
    {
      "lap": 51,
      "split_sec": 734.57,
      "cum_sec": 30574.33
    },
    {
      "lap": 52,
      "split_sec": 685.74,
      "cum_sec": 31260.07
    },
    {
      "lap": 53,
      "split_sec": 800.81,
      "cum_sec": 32060.87
    },
    {
      "lap": 54,
      "split_sec": 1087.81,
      "cum_sec": 33148.68
    },
    {
      "lap": 55,
      "split_sec": 633.53,
      "cum_sec": 33782.21
    },
    {
      "lap": 56,
      "split_sec": 534.05,
      "cum_sec": 34316.25
    },
    {
      "lap": 57,
      "split_sec": 744.4,
      "cum_sec": 35060.65
    },
    {
      "lap": 58,
      "split_sec": 630.96,
      "cum_sec": 35691.6
    },
    {
      "lap": 59,
      "split_sec": 1189.18,
      "cum_sec": 36880.78
    },
    {
      "lap": 60,
      "split_sec": 568.37,
      "cum_sec": 37449.15
    },
    {
      "lap": 61,
      "split_sec": 1345.62,
      "cum_sec": 38794.76
    },
    {
      "lap": 62,
      "split_sec": 588.43,
      "cum_sec": 39383.18
    },
    {
      "lap": 63,
      "split_sec": 725.22,
      "cum_sec": 40108.4
    },
    {
      "lap": 64,
      "split_sec": 824.83,
      "cum_sec": 40933.23
    },
    {
      "lap": 65,
      "split_sec": 616.72,
      "cum_sec": 41549.94
    },
    {
      "lap": 66,
      "split_sec": 622.77,
      "cum_sec": 42172.71
    },
    {
      "lap": 67,
      "split_sec": 1027.1,
      "cum_sec": 43199.8
    },
    {
      "lap": 68,
      "split_sec": 1176.66,
      "cum_sec": 44376.46
    },
    {
      "lap": 69,
      "split_sec": 624.61,
      "cum_sec": 45001.06
    },
    {
      "lap": 70,
      "split_sec": 1357.44,
      "cum_sec": 46358.5
    },
    {
      "lap": 71,
      "split_sec": 632.16,
      "cum_sec": 46990.65
    },
    {
      "lap": 72,
      "split_sec": 599.43,
      "cum_sec": 47590.08
    },
    {
      "lap": 73,
      "split_sec": 860.86,
      "cum_sec": 48450.93
    },
    {
      "lap": 74,
      "split_sec": 647.6,
      "cum_sec": 49098.53
    },
    {
      "lap": 75,
      "split_sec": 2423.09,
      "cum_sec": 51521.61
    },
    {
      "lap": 76,
      "split_sec": 827.59,
      "cum_sec": 52349.2
    },
    {
      "lap": 77,
      "split_sec": 871.28,
      "cum_sec": 53220.47
    },
    {
      "lap": 78,
      "split_sec": 860.71,
      "cum_sec": 54081.18
    },
    {
      "lap": 79,
      "split_sec": 696.54,
      "cum_sec": 54777.71
    },
    {
      "lap": 80,
      "split_sec": 670.92,
      "cum_sec": 55448.62
    },
    {
      "lap": 81,
      "split_sec": 3654.67,
      "cum_sec": 59103.29
    },
    {
      "lap": 82,
      "split_sec": 775.23,
      "cum_sec": 59878.51
    },
    {
      "lap": 83,
      "split_sec": 743.17,
      "cum_sec": 60621.67
    },
    {
      "lap": 84,
      "split_sec": 1034.04,
      "cum_sec": 61655.71
    },
    {
      "lap": 85,
      "split_sec": 462.95,
      "cum_sec": 62118.65
    },
    {
      "lap": 86,
      "split_sec": 461.52,
      "cum_sec": 62580.17
    },
    {
      "lap": 87,
      "split_sec": 533.95,
      "cum_sec": 63114.11
    },
    {
      "lap": 88,
      "split_sec": 524.07,
      "cum_sec": 63638.18
    },
    {
      "lap": 89,
      "split_sec": 520.71,
      "cum_sec": 64158.89
    },
    {
      "lap": 90,
      "split_sec": 533.27,
      "cum_sec": 64692.15
    },
    {
      "lap": 91,
      "split_sec": 770.17,
      "cum_sec": 65462.32
    },
    {
      "lap": 92,
      "split_sec": 559.12,
      "cum_sec": 66021.43
    },
    {
      "lap": 93,
      "split_sec": 547.38,
      "cum_sec": 66568.81
    },
    {
      "lap": 94,
      "split_sec": 590.48,
      "cum_sec": 67159.28
    },
    {
      "lap": 95,
      "split_sec": 2185.72,
      "cum_sec": 69344.99
    },
    {
      "lap": 96,
      "split_sec": 838.59,
      "cum_sec": 70183.58
    },
    {
      "lap": 97,
      "split_sec": 821.46,
      "cum_sec": 71005.03
    },
    {
      "lap": 98,
      "split_sec": 868.67,
      "cum_sec": 71873.7
    },
    {
      "lap": 99,
      "split_sec": 928.04,
      "cum_sec": 72801.73
    },
    {
      "lap": 100,
      "split_sec": 1040.07,
      "cum_sec": 73841.79
    },
    {
      "lap": 101,
      "split_sec": 1091.82,
      "cum_sec": 74933.61
    },
    {
      "lap": 102,
      "split_sec": 555.55,
      "cum_sec": 75489.16
    },
    {
      "lap": 103,
      "split_sec": 554.17,
      "cum_sec": 76043.33
    },
    {
      "lap": 104,
      "split_sec": 570.34,
      "cum_sec": 76613.66
    },
    {
      "lap": 105,
      "split_sec": 642.21,
      "cum_sec": 77255.87
    },
    {
      "lap": 106,
      "split_sec": 615.13,
      "cum_sec": 77871
    },
    {
      "lap": 107,
      "split_sec": 641.09,
      "cum_sec": 78512.08
    },
    {
      "lap": 108,
      "split_sec": 720.25,
      "cum_sec": 79232.32
    },
    {
      "lap": 109,
      "split_sec": 611.23,
      "cum_sec": 79843.55
    },
    {
      "lap": 110,
      "split_sec": 599.79,
      "cum_sec": 80443.34
    },
    {
      "lap": 111,
      "split_sec": 626.84,
      "cum_sec": 81070.17
    },
    {
      "lap": 112,
      "split_sec": 641.06,
      "cum_sec": 81711.22
    },
    {
      "lap": 113,
      "split_sec": 1639.32,
      "cum_sec": 83350.54
    },
    {
      "lap": 114,
      "split_sec": 1104.74,
      "cum_sec": 84455.27
    },
    {
      "lap": 115,
      "split_sec": 1323.65,
      "cum_sec": 85778.92
    },
    {
      "lap": 116,
      "split_sec": 512.82,
      "cum_sec": 86291.73
    }
  ],
  "duration_sec": 86291.73,
  "distance_mi": 86.42,
  "loop_distance_mi": 0.745,
  "duration": "23:58:11"
}
