{
  "runner": "Alexis Petersen",
  "race": "Across the Years",
  "year": 2024,
  "distance_mi": 21.16,
  "distance_id": "6h",
  "duration_sec": 21600,
  "duration": "6:00:00",
  "data_type": "miles",
  "source": "live.aravaiparunning.com event 376",
  "gender": "F",
  "loop_meters": 2270.6,
  "total_laps": 15,
  "miles": [
    {
      "mile": 1,
      "split_sec": 892.1,
      "moving_sec": 892.1,
      "cum_sec": 892.1
    },
    {
      "mile": 2,
      "split_sec": 938.3,
      "moving_sec": 938.3,
      "cum_sec": 1830.4
    },
    {
      "mile": 3,
      "split_sec": 957.8,
      "moving_sec": 957.8,
      "cum_sec": 2788.2
    },
    {
      "mile": 4,
      "split_sec": 899.2,
      "moving_sec": 899.2,
      "cum_sec": 3687.4
    },
    {
      "mile": 5,
      "split_sec": 905.6,
      "moving_sec": 905.6,
      "cum_sec": 4593.0
    },
    {
      "mile": 6,
      "split_sec": 919.8,
      "moving_sec": 919.8,
      "cum_sec": 5512.8
    },
    {
      "mile": 7,
      "split_sec": 941.9,
      "moving_sec": 941.9,
      "cum_sec": 6454.7
    },
    {
      "mile": 8,
      "split_sec": 894.1,
      "moving_sec": 894.1,
      "cum_sec": 7348.8
    },
    {
      "mile": 9,
      "split_sec": 909.7,
      "moving_sec": 909.7,
      "cum_sec": 8258.5
    },
    {
      "mile": 10,
      "split_sec": 971.8,
      "moving_sec": 971.8,
      "cum_sec": 9230.3
    },
    {
      "mile": 11,
      "split_sec": 1298.4,
      "moving_sec": 1298.4,
      "cum_sec": 10528.7
    },
    {
      "mile": 12,
      "split_sec": 1236.9,
      "moving_sec": 1236.9,
      "cum_sec": 11765.7
    },
    {
      "mile": 13,
      "split_sec": 1123.3,
      "moving_sec": 1123.3,
      "cum_sec": 12889.0
    },
    {
      "mile": 14,
      "split_sec": 917.9,
      "moving_sec": 917.9,
      "cum_sec": 13806.9
    },
    {
      "mile": 15,
      "split_sec": 939.5,
      "moving_sec": 939.5,
      "cum_sec": 14746.4
    },
    {
      "mile": 16,
      "split_sec": 943.7,
      "moving_sec": 943.7,
      "cum_sec": 15690.1
    },
    {
      "mile": 17,
      "split_sec": 952.0,
      "moving_sec": 952.0,
      "cum_sec": 16642.2
    },
    {
      "mile": 18,
      "split_sec": 1041.3,
      "moving_sec": 1041.3,
      "cum_sec": 17683.5
    },
    {
      "mile": 19,
      "split_sec": 1001.7,
      "moving_sec": 1001.7,
      "cum_sec": 18685.1
    },
    {
      "mile": 20,
      "split_sec": 964.0,
      "moving_sec": 964.0,
      "cum_sec": 19649.2
    },
    {
      "mile": 21,
      "split_sec": 912.3,
      "moving_sec": 912.3,
      "cum_sec": 20561.5
    }
  ]
}
