{
  "runner": "Ken Haynie",
  "race": "Across the Years",
  "year": 2023,
  "distance_mi": 56.35,
  "distance_id": "48h",
  "duration_sec": 172800,
  "duration": "48:00:00",
  "data_type": "miles",
  "source": "live.aravaiparunning.com event 295",
  "gender": "M",
  "loop_meters": 2267.0,
  "total_laps": 40,
  "miles": [
    {
      "mile": 1,
      "split_sec": 1007.5,
      "moving_sec": 1007.5,
      "cum_sec": 1007.5
    },
    {
      "mile": 2,
      "split_sec": 1035.2,
      "moving_sec": 1035.2,
      "cum_sec": 2042.7
    },
    {
      "mile": 3,
      "split_sec": 1054.5,
      "moving_sec": 1054.5,
      "cum_sec": 3097.2
    },
    {
      "mile": 4,
      "split_sec": 1055.4,
      "moving_sec": 1055.4,
      "cum_sec": 4152.6
    },
    {
      "mile": 5,
      "split_sec": 1067.3,
      "moving_sec": 1067.3,
      "cum_sec": 5219.9
    },
    {
      "mile": 6,
      "split_sec": 1076.3,
      "moving_sec": 1076.3,
      "cum_sec": 6296.2
    },
    {
      "mile": 7,
      "split_sec": 1086.0,
      "moving_sec": 1086.0,
      "cum_sec": 7382.2
    },
    {
      "mile": 8,
      "split_sec": 1709.5,
      "moving_sec": 1709.5,
      "cum_sec": 9091.7
    },
    {
      "mile": 9,
      "split_sec": 1380.8,
      "moving_sec": 1380.8,
      "cum_sec": 10472.5
    },
    {
      "mile": 10,
      "split_sec": 1084.5,
      "moving_sec": 1084.5,
      "cum_sec": 11557.1
    },
    {
      "mile": 11,
      "split_sec": 1071.6,
      "moving_sec": 1071.6,
      "cum_sec": 12628.6
    },
    {
      "mile": 12,
      "split_sec": 1112.2,
      "moving_sec": 1112.2,
      "cum_sec": 13740.8
    },
    {
      "mile": 13,
      "split_sec": 1161.5,
      "moving_sec": 1161.5,
      "cum_sec": 14902.3
    },
    {
      "mile": 14,
      "split_sec": 1233.9,
      "moving_sec": 1233.9,
      "cum_sec": 16136.3
    },
    {
      "mile": 15,
      "split_sec": 3027.8,
      "moving_sec": 3027.8,
      "cum_sec": 19164.1
    },
    {
      "mile": 16,
      "split_sec": 2166.0,
      "moving_sec": 2166.0,
      "cum_sec": 21330.1
    },
    {
      "mile": 17,
      "split_sec": 1158.5,
      "moving_sec": 1158.5,
      "cum_sec": 22488.5
    },
    {
      "mile": 18,
      "split_sec": 1183.7,
      "moving_sec": 1183.7,
      "cum_sec": 23672.2
    },
    {
      "mile": 19,
      "split_sec": 1138.4,
      "moving_sec": 1138.4,
      "cum_sec": 24810.6
    },
    {
      "mile": 20,
      "split_sec": 1303.4,
      "moving_sec": 1303.4,
      "cum_sec": 26113.9
    },
    {
      "mile": 21,
      "split_sec": 1782.8,
      "moving_sec": 1782.8,
      "cum_sec": 27896.7
    },
    {
      "mile": 22,
      "split_sec": 1391.9,
      "moving_sec": 1391.9,
      "cum_sec": 29288.7
    },
    {
      "mile": 23,
      "split_sec": 1290.1,
      "moving_sec": 1290.1,
      "cum_sec": 30578.8
    },
    {
      "mile": 24,
      "split_sec": 1244.6,
      "moving_sec": 1244.6,
      "cum_sec": 31823.4
    },
    {
      "mile": 25,
      "split_sec": 1335.3,
      "moving_sec": 1335.3,
      "cum_sec": 33158.6
    },
    {
      "mile": 26,
      "split_sec": 1294.6,
      "moving_sec": 1294.6,
      "cum_sec": 34453.2
    },
    {
      "mile": 27,
      "split_sec": 2745.4,
      "moving_sec": 2745.4,
      "cum_sec": 37198.7
    }
  ]
}
