{
  "runner": "Jill Aderhold",
  "race": "Across The Years Ultras",
  "year": 2022,
  "distance_id": "6h",
  "source": "my.raceresult.com event 229460",
  "gender": "F",
  "data_type": "miles",
  "distance_mi": 32.4,
  "duration_sec": 21226,
  "loop_meters": 2267.0,
  "total_laps": 23,
  "miles": [
    {
      "mile": 1,
      "split_sec": 470.0,
      "moving_sec": 470.0,
      "cum_sec": 470.0
    },
    {
      "mile": 2,
      "split_sec": 495.1,
      "moving_sec": 495.1,
      "cum_sec": 965.1
    },
    {
      "mile": 3,
      "split_sec": 507.2,
      "moving_sec": 507.2,
      "cum_sec": 1472.3
    },
    {
      "mile": 4,
      "split_sec": 483.4,
      "moving_sec": 483.4,
      "cum_sec": 1955.8
    },
    {
      "mile": 5,
      "split_sec": 491.7,
      "moving_sec": 491.7,
      "cum_sec": 2447.5
    },
    {
      "mile": 6,
      "split_sec": 501.1,
      "moving_sec": 501.1,
      "cum_sec": 2948.5
    },
    {
      "mile": 7,
      "split_sec": 513.3,
      "moving_sec": 513.3,
      "cum_sec": 3461.8
    },
    {
      "mile": 8,
      "split_sec": 532.3,
      "moving_sec": 532.3,
      "cum_sec": 3994.1
    },
    {
      "mile": 9,
      "split_sec": 523.4,
      "moving_sec": 523.4,
      "cum_sec": 4517.5
    },
    {
      "mile": 10,
      "split_sec": 517.4,
      "moving_sec": 517.4,
      "cum_sec": 5034.9
    },
    {
      "mile": 11,
      "split_sec": 529.6,
      "moving_sec": 529.6,
      "cum_sec": 5564.4
    },
    {
      "mile": 12,
      "split_sec": 650.5,
      "moving_sec": 650.5,
      "cum_sec": 6214.9
    },
    {
      "mile": 13,
      "split_sec": 846.9,
      "moving_sec": 846.9,
      "cum_sec": 7061.8
    },
    {
      "mile": 14,
      "split_sec": 1166.4,
      "moving_sec": 1166.4,
      "cum_sec": 8228.1
    },
    {
      "mile": 15,
      "split_sec": 584.7,
      "moving_sec": 584.7,
      "cum_sec": 8812.8
    },
    {
      "mile": 16,
      "split_sec": 565.8,
      "moving_sec": 565.8,
      "cum_sec": 9378.6
    },
    {
      "mile": 17,
      "split_sec": 600.5,
      "moving_sec": 600.5,
      "cum_sec": 9979.0
    },
    {
      "mile": 18,
      "split_sec": 592.8,
      "moving_sec": 592.8,
      "cum_sec": 10571.8
    },
    {
      "mile": 19,
      "split_sec": 949.1,
      "moving_sec": 949.1,
      "cum_sec": 11520.9
    },
    {
      "mile": 20,
      "split_sec": 955.6,
      "moving_sec": 955.6,
      "cum_sec": 12476.4
    },
    {
      "mile": 21,
      "split_sec": 553.7,
      "moving_sec": 553.7,
      "cum_sec": 13030.2
    },
    {
      "mile": 22,
      "split_sec": 805.2,
      "moving_sec": 805.2,
      "cum_sec": 13835.3
    },
    {
      "mile": 23,
      "split_sec": 707.6,
      "moving_sec": 707.6,
      "cum_sec": 14543.0
    },
    {
      "mile": 24,
      "split_sec": 557.6,
      "moving_sec": 557.6,
      "cum_sec": 15100.6
    },
    {
      "mile": 25,
      "split_sec": 690.0,
      "moving_sec": 690.0,
      "cum_sec": 15790.6
    },
    {
      "mile": 26,
      "split_sec": 760.9,
      "moving_sec": 760.9,
      "cum_sec": 16551.5
    },
    {
      "mile": 27,
      "split_sec": 758.4,
      "moving_sec": 758.4,
      "cum_sec": 17309.9
    },
    {
      "mile": 28,
      "split_sec": 623.3,
      "moving_sec": 623.3,
      "cum_sec": 17933.2
    },
    {
      "mile": 29,
      "split_sec": 753.0,
      "moving_sec": 753.0,
      "cum_sec": 18686.2
    },
    {
      "mile": 30,
      "split_sec": 753.2,
      "moving_sec": 753.2,
      "cum_sec": 19439.4
    },
    {
      "mile": 31,
      "split_sec": 716.1,
      "moving_sec": 716.1,
      "cum_sec": 20155.4
    },
    {
      "mile": 32,
      "split_sec": 765.3,
      "moving_sec": 765.3,
      "cum_sec": 20920.7
    }
  ]
}
