{
  "runner": "Wayne Williams",
  "race": "Beyond Limits Ultras",
  "year": 2025,
  "distance_mi": 64.0,
  "distance_id": "24h",
  "duration_sec": 86400,
  "duration": "24:00:00",
  "data_type": "miles",
  "source": "live.aravaiparunning.com event 396",
  "gender": "M",
  "loop_meters": 3218.69,
  "total_laps": 32,
  "miles": [
    {
      "mile": 1,
      "split_sec": 597.0,
      "moving_sec": 597.0,
      "cum_sec": 597.0
    },
    {
      "mile": 2,
      "split_sec": 597.0,
      "moving_sec": 597.0,
      "cum_sec": 1193.9
    },
    {
      "mile": 3,
      "split_sec": 693.8,
      "moving_sec": 693.8,
      "cum_sec": 1887.8
    },
    {
      "mile": 4,
      "split_sec": 693.8,
      "moving_sec": 693.8,
      "cum_sec": 2581.6
    },
    {
      "mile": 5,
      "split_sec": 768.1,
      "moving_sec": 768.1,
      "cum_sec": 3349.7
    },
    {
      "mile": 6,
      "split_sec": 768.1,
      "moving_sec": 768.1,
      "cum_sec": 4117.8
    },
    {
      "mile": 7,
      "split_sec": 781.1,
      "moving_sec": 781.1,
      "cum_sec": 4898.9
    },
    {
      "mile": 8,
      "split_sec": 781.0,
      "moving_sec": 781.0,
      "cum_sec": 5679.9
    },
    {
      "mile": 9,
      "split_sec": 866.1,
      "moving_sec": 866.1,
      "cum_sec": 6545.9
    },
    {
      "mile": 10,
      "split_sec": 866.1,
      "moving_sec": 866.1,
      "cum_sec": 7412.0
    },
    {
      "mile": 11,
      "split_sec": 781.4,
      "moving_sec": 781.4,
      "cum_sec": 8193.4
    },
    {
      "mile": 12,
      "split_sec": 781.4,
      "moving_sec": 781.4,
      "cum_sec": 8974.7
    },
    {
      "mile": 13,
      "split_sec": 952.0,
      "moving_sec": 952.0,
      "cum_sec": 9926.8
    },
    {
      "mile": 14,
      "split_sec": 952.0,
      "moving_sec": 952.0,
      "cum_sec": 10878.8
    },
    {
      "mile": 15,
      "split_sec": 1145.0,
      "moving_sec": 1145.0,
      "cum_sec": 12023.8
    },
    {
      "mile": 16,
      "split_sec": 1145.0,
      "moving_sec": 1145.0,
      "cum_sec": 13168.7
    },
    {
      "mile": 17,
      "split_sec": 1017.8,
      "moving_sec": 1017.8,
      "cum_sec": 14186.5
    },
    {
      "mile": 18,
      "split_sec": 1017.9,
      "moving_sec": 1017.9,
      "cum_sec": 15204.4
    },
    {
      "mile": 19,
      "split_sec": 898.3,
      "moving_sec": 898.3,
      "cum_sec": 16102.7
    },
    {
      "mile": 20,
      "split_sec": 898.2,
      "moving_sec": 898.2,
      "cum_sec": 17000.9
    },
    {
      "mile": 21,
      "split_sec": 859.6,
      "moving_sec": 859.6,
      "cum_sec": 17860.5
    },
    {
      "mile": 22,
      "split_sec": 859.6,
      "moving_sec": 859.6,
      "cum_sec": 18720.1
    },
    {
      "mile": 23,
      "split_sec": 1329.3,
      "moving_sec": 1329.3,
      "cum_sec": 20049.4
    },
    {
      "mile": 24,
      "split_sec": 1329.4,
      "moving_sec": 1329.4,
      "cum_sec": 21378.8
    },
    {
      "mile": 25,
      "split_sec": 1298.8,
      "moving_sec": 1298.8,
      "cum_sec": 22677.6
    },
    {
      "mile": 26,
      "split_sec": 1298.8,
      "moving_sec": 1298.8,
      "cum_sec": 23976.4
    },
    {
      "mile": 27,
      "split_sec": 1120.1,
      "moving_sec": 1120.1,
      "cum_sec": 25096.5
    },
    {
      "mile": 28,
      "split_sec": 1120.1,
      "moving_sec": 1120.1,
      "cum_sec": 26216.6
    },
    {
      "mile": 29,
      "split_sec": 1190.2,
      "moving_sec": 1190.2,
      "cum_sec": 27406.8
    },
    {
      "mile": 30,
      "split_sec": 1190.2,
      "moving_sec": 1190.2,
      "cum_sec": 28597.0
    },
    {
      "mile": 31,
      "split_sec": 1495.9,
      "moving_sec": 1495.9,
      "cum_sec": 30092.9
    },
    {
      "mile": 32,
      "split_sec": 1495.9,
      "moving_sec": 1495.9,
      "cum_sec": 31588.8
    },
    {
      "mile": 33,
      "split_sec": 1692.2,
      "moving_sec": 1692.2,
      "cum_sec": 33281.0
    },
    {
      "mile": 34,
      "split_sec": 1692.2,
      "moving_sec": 1692.2,
      "cum_sec": 34973.2
    },
    {
      "mile": 35,
      "split_sec": 1386.9,
      "moving_sec": 1386.9,
      "cum_sec": 36360.1
    },
    {
      "mile": 36,
      "split_sec": 1386.9,
      "moving_sec": 1386.9,
      "cum_sec": 37747.0
    },
    {
      "mile": 37,
      "split_sec": 1136.6,
      "moving_sec": 1136.6,
      "cum_sec": 38883.6
    },
    {
      "mile": 38,
      "split_sec": 1136.5,
      "moving_sec": 1136.5,
      "cum_sec": 40020.1
    },
    {
      "mile": 39,
      "split_sec": 1006.8,
      "moving_sec": 1006.8,
      "cum_sec": 41026.8
    },
    {
      "mile": 40,
      "split_sec": 1006.8,
      "moving_sec": 1006.8,
      "cum_sec": 42033.6
    },
    {
      "mile": 41,
      "split_sec": 1402.3,
      "moving_sec": 1402.3,
      "cum_sec": 43435.9
    },
    {
      "mile": 42,
      "split_sec": 1402.3,
      "moving_sec": 1402.3,
      "cum_sec": 44838.2
    },
    {
      "mile": 43,
      "split_sec": 1411.3,
      "moving_sec": 1411.3,
      "cum_sec": 46249.5
    },
    {
      "mile": 44,
      "split_sec": 1411.3,
      "moving_sec": 1411.3,
      "cum_sec": 47660.8
    },
    {
      "mile": 45,
      "split_sec": 1168.6,
      "moving_sec": 1168.6,
      "cum_sec": 48829.4
    },
    {
      "mile": 46,
      "split_sec": 1168.7,
      "moving_sec": 1168.7,
      "cum_sec": 49998.1
    },
    {
      "mile": 47,
      "split_sec": 1214.0,
      "moving_sec": 1214.0,
      "cum_sec": 51212.1
    },
    {
      "mile": 48,
      "split_sec": 1213.9,
      "moving_sec": 1213.9,
      "cum_sec": 52426.0
    },
    {
      "mile": 49,
      "split_sec": 1512.8,
      "moving_sec": 1512.8,
      "cum_sec": 53938.8
    },
    {
      "mile": 50,
      "split_sec": 1512.8,
      "moving_sec": 1512.8,
      "cum_sec": 55451.6
    }
  ]
}
