{
  "runner": "Chris Vander Linden",
  "race": "Chase the Moon",
  "year": 2025,
  "distance_mi": 41.21,
  "distance_id": "12h",
  "duration_sec": 43200,
  "duration": "12:00:00",
  "data_type": "miles",
  "source": "live.aravaiparunning.com event 422",
  "gender": "M",
  "loop_meters": 16580.0,
  "total_laps": 4,
  "miles": [
    {
      "mile": 1,
      "split_sec": 534.3,
      "moving_sec": 534.3,
      "cum_sec": 534.3
    },
    {
      "mile": 2,
      "split_sec": 534.3,
      "moving_sec": 534.3,
      "cum_sec": 1068.7
    },
    {
      "mile": 3,
      "split_sec": 534.3,
      "moving_sec": 534.3,
      "cum_sec": 1603.0
    },
    {
      "mile": 4,
      "split_sec": 534.3,
      "moving_sec": 534.3,
      "cum_sec": 2137.4
    },
    {
      "mile": 5,
      "split_sec": 534.3,
      "moving_sec": 534.3,
      "cum_sec": 2671.7
    },
    {
      "mile": 6,
      "split_sec": 534.3,
      "moving_sec": 534.3,
      "cum_sec": 3206.1
    },
    {
      "mile": 7,
      "split_sec": 534.3,
      "moving_sec": 534.3,
      "cum_sec": 3740.4
    },
    {
      "mile": 8,
      "split_sec": 534.3,
      "moving_sec": 534.3,
      "cum_sec": 4274.7
    },
    {
      "mile": 9,
      "split_sec": 534.3,
      "moving_sec": 534.3,
      "cum_sec": 4809.1
    },
    {
      "mile": 10,
      "split_sec": 534.3,
      "moving_sec": 534.3,
      "cum_sec": 5343.4
    },
    {
      "mile": 11,
      "split_sec": 660.4,
      "moving_sec": 660.4,
      "cum_sec": 6003.8
    },
    {
      "mile": 12,
      "split_sec": 714.9,
      "moving_sec": 714.9,
      "cum_sec": 6718.6
    },
    {
      "mile": 13,
      "split_sec": 714.9,
      "moving_sec": 714.9,
      "cum_sec": 7433.5
    },
    {
      "mile": 14,
      "split_sec": 714.9,
      "moving_sec": 714.9,
      "cum_sec": 8148.4
    },
    {
      "mile": 15,
      "split_sec": 714.9,
      "moving_sec": 714.9,
      "cum_sec": 8863.3
    },
    {
      "mile": 16,
      "split_sec": 714.9,
      "moving_sec": 714.9,
      "cum_sec": 9578.1
    },
    {
      "mile": 17,
      "split_sec": 714.9,
      "moving_sec": 714.9,
      "cum_sec": 10293.0
    },
    {
      "mile": 18,
      "split_sec": 714.9,
      "moving_sec": 714.9,
      "cum_sec": 11007.9
    },
    {
      "mile": 19,
      "split_sec": 714.9,
      "moving_sec": 714.9,
      "cum_sec": 11722.7
    },
    {
      "mile": 20,
      "split_sec": 714.9,
      "moving_sec": 714.9,
      "cum_sec": 12437.6
    },
    {
      "mile": 21,
      "split_sec": 780.7,
      "moving_sec": 780.7,
      "cum_sec": 13218.3
    },
    {
      "mile": 22,
      "split_sec": 881.6,
      "moving_sec": 881.6,
      "cum_sec": 14099.9
    },
    {
      "mile": 23,
      "split_sec": 881.6,
      "moving_sec": 881.6,
      "cum_sec": 14981.5
    },
    {
      "mile": 24,
      "split_sec": 881.6,
      "moving_sec": 881.6,
      "cum_sec": 15863.1
    },
    {
      "mile": 25,
      "split_sec": 881.6,
      "moving_sec": 881.6,
      "cum_sec": 16744.7
    },
    {
      "mile": 26,
      "split_sec": 881.6,
      "moving_sec": 881.6,
      "cum_sec": 17626.3
    },
    {
      "mile": 27,
      "split_sec": 881.6,
      "moving_sec": 881.6,
      "cum_sec": 18507.8
    },
    {
      "mile": 28,
      "split_sec": 881.6,
      "moving_sec": 881.6,
      "cum_sec": 19389.4
    },
    {
      "mile": 29,
      "split_sec": 881.6,
      "moving_sec": 881.6,
      "cum_sec": 20271.0
    },
    {
      "mile": 30,
      "split_sec": 881.6,
      "moving_sec": 881.6,
      "cum_sec": 21152.6
    },
    {
      "mile": 31,
      "split_sec": 885.3,
      "moving_sec": 885.3,
      "cum_sec": 22037.9
    },
    {
      "mile": 32,
      "split_sec": 921.6,
      "moving_sec": 921.6,
      "cum_sec": 22959.5
    },
    {
      "mile": 33,
      "split_sec": 921.6,
      "moving_sec": 921.6,
      "cum_sec": 23881.1
    },
    {
      "mile": 34,
      "split_sec": 921.6,
      "moving_sec": 921.6,
      "cum_sec": 24802.7
    },
    {
      "mile": 35,
      "split_sec": 921.6,
      "moving_sec": 921.6,
      "cum_sec": 25724.3
    },
    {
      "mile": 36,
      "split_sec": 921.6,
      "moving_sec": 921.6,
      "cum_sec": 26645.9
    },
    {
      "mile": 37,
      "split_sec": 921.6,
      "moving_sec": 921.6,
      "cum_sec": 27567.5
    },
    {
      "mile": 38,
      "split_sec": 921.6,
      "moving_sec": 921.6,
      "cum_sec": 28489.1
    },
    {
      "mile": 39,
      "split_sec": 921.6,
      "moving_sec": 921.6,
      "cum_sec": 29410.7
    },
    {
      "mile": 40,
      "split_sec": 921.6,
      "moving_sec": 921.6,
      "cum_sec": 30332.3
    },
    {
      "mile": 41,
      "split_sec": 921.6,
      "moving_sec": 921.6,
      "cum_sec": 31253.9
    }
  ]
}
