{
  "runner": "Steven Anderson",
  "race": "Hotfoot Hamster",
  "year": 2023,
  "distance_mi": 26.72,
  "distance_id": "6h",
  "duration_sec": 21600,
  "duration": "6:00:00",
  "data_type": "miles",
  "source": "live.aravaiparunning.com event 257",
  "gender": "M",
  "loop_meters": 500.0,
  "total_laps": 86,
  "miles": [
    {
      "mile": 1,
      "split_sec": 572.7,
      "moving_sec": 572.7,
      "cum_sec": 572.7
    },
    {
      "mile": 2,
      "split_sec": 592.8,
      "moving_sec": 592.8,
      "cum_sec": 1165.5
    },
    {
      "mile": 3,
      "split_sec": 617.5,
      "moving_sec": 617.5,
      "cum_sec": 1783.0
    },
    {
      "mile": 4,
      "split_sec": 633.6,
      "moving_sec": 633.6,
      "cum_sec": 2416.6
    },
    {
      "mile": 5,
      "split_sec": 630.3,
      "moving_sec": 630.3,
      "cum_sec": 3046.9
    },
    {
      "mile": 6,
      "split_sec": 726.2,
      "moving_sec": 726.2,
      "cum_sec": 3773.1
    },
    {
      "mile": 7,
      "split_sec": 715.5,
      "moving_sec": 715.5,
      "cum_sec": 4488.6
    },
    {
      "mile": 8,
      "split_sec": 685.7,
      "moving_sec": 685.7,
      "cum_sec": 5174.3
    },
    {
      "mile": 9,
      "split_sec": 690.1,
      "moving_sec": 690.1,
      "cum_sec": 5864.4
    },
    {
      "mile": 10,
      "split_sec": 703.8,
      "moving_sec": 703.8,
      "cum_sec": 6568.1
    },
    {
      "mile": 11,
      "split_sec": 874.9,
      "moving_sec": 874.9,
      "cum_sec": 7443.0
    },
    {
      "mile": 12,
      "split_sec": 885.0,
      "moving_sec": 885.0,
      "cum_sec": 8328.1
    },
    {
      "mile": 13,
      "split_sec": 763.7,
      "moving_sec": 763.7,
      "cum_sec": 9091.7
    },
    {
      "mile": 14,
      "split_sec": 707.2,
      "moving_sec": 707.2,
      "cum_sec": 9798.9
    },
    {
      "mile": 15,
      "split_sec": 974.7,
      "moving_sec": 974.7,
      "cum_sec": 10773.5
    },
    {
      "mile": 16,
      "split_sec": 919.2,
      "moving_sec": 919.2,
      "cum_sec": 11692.7
    },
    {
      "mile": 17,
      "split_sec": 880.2,
      "moving_sec": 880.2,
      "cum_sec": 12572.9
    },
    {
      "mile": 18,
      "split_sec": 750.0,
      "moving_sec": 750.0,
      "cum_sec": 13322.9
    },
    {
      "mile": 19,
      "split_sec": 891.4,
      "moving_sec": 891.4,
      "cum_sec": 14214.3
    },
    {
      "mile": 20,
      "split_sec": 895.6,
      "moving_sec": 895.6,
      "cum_sec": 15109.9
    },
    {
      "mile": 21,
      "split_sec": 990.1,
      "moving_sec": 990.1,
      "cum_sec": 16100.0
    },
    {
      "mile": 22,
      "split_sec": 879.4,
      "moving_sec": 879.4,
      "cum_sec": 16979.4
    },
    {
      "mile": 23,
      "split_sec": 853.9,
      "moving_sec": 853.9,
      "cum_sec": 17833.4
    },
    {
      "mile": 24,
      "split_sec": 981.6,
      "moving_sec": 981.6,
      "cum_sec": 18815.0
    },
    {
      "mile": 25,
      "split_sec": 882.0,
      "moving_sec": 882.0,
      "cum_sec": 19697.0
    },
    {
      "mile": 26,
      "split_sec": 1030.1,
      "moving_sec": 1030.1,
      "cum_sec": 20727.1
    }
  ]
}
