{
  "runner": "Donna Buckley",
  "race": "Hotfoot Hamster",
  "year": 2024,
  "distance_mi": 10.87,
  "distance_id": "12h",
  "duration_sec": 43200,
  "duration": "12:00:00",
  "data_type": "miles",
  "source": "live.aravaiparunning.com event 326",
  "gender": "F",
  "loop_meters": 500.0,
  "total_laps": 35,
  "miles": [
    {
      "mile": 1,
      "split_sec": 1012.9,
      "moving_sec": 1012.9,
      "cum_sec": 1012.9
    },
    {
      "mile": 2,
      "split_sec": 1365.1,
      "moving_sec": 1365.1,
      "cum_sec": 2377.9
    },
    {
      "mile": 3,
      "split_sec": 1206.6,
      "moving_sec": 1206.6,
      "cum_sec": 3584.5
    },
    {
      "mile": 4,
      "split_sec": 1181.6,
      "moving_sec": 1181.6,
      "cum_sec": 4766.2
    },
    {
      "mile": 5,
      "split_sec": 2117.5,
      "moving_sec": 2117.5,
      "cum_sec": 6883.7
    },
    {
      "mile": 6,
      "split_sec": 1107.0,
      "moving_sec": 1107.0,
      "cum_sec": 7990.6
    },
    {
      "mile": 7,
      "split_sec": 1526.4,
      "moving_sec": 1526.4,
      "cum_sec": 9517.0
    },
    {
      "mile": 8,
      "split_sec": 4215.5,
      "moving_sec": 4215.5,
      "cum_sec": 13732.6
    },
    {
      "mile": 9,
      "split_sec": 2131.2,
      "moving_sec": 2131.2,
      "cum_sec": 15863.8
    },
    {
      "mile": 10,
      "split_sec": 2829.1,
      "moving_sec": 2829.1,
      "cum_sec": 18692.9
    }
  ]
}
