{
  "runner": "Diosa Holmes",
  "race": "Jackrabbit Jubilee",
  "year": 2021,
  "distance_mi": 24.85,
  "distance_id": "6h",
  "duration_sec": 21600,
  "duration": "6:00:00",
  "data_type": "miles",
  "source": "live.aravaiparunning.com event 144",
  "gender": "F",
  "loop_meters": 500.0,
  "total_laps": 80,
  "miles": [
    {
      "mile": 1,
      "split_sec": 628.5,
      "moving_sec": 628.5,
      "cum_sec": 628.5
    },
    {
      "mile": 2,
      "split_sec": 595.1,
      "moving_sec": 595.1,
      "cum_sec": 1223.6
    },
    {
      "mile": 3,
      "split_sec": 589.7,
      "moving_sec": 589.7,
      "cum_sec": 1813.3
    },
    {
      "mile": 4,
      "split_sec": 590.7,
      "moving_sec": 590.7,
      "cum_sec": 2404.0
    },
    {
      "mile": 5,
      "split_sec": 590.5,
      "moving_sec": 590.5,
      "cum_sec": 2994.5
    },
    {
      "mile": 6,
      "split_sec": 663.8,
      "moving_sec": 663.8,
      "cum_sec": 3658.3
    },
    {
      "mile": 7,
      "split_sec": 747.7,
      "moving_sec": 747.7,
      "cum_sec": 4406.0
    },
    {
      "mile": 8,
      "split_sec": 777.0,
      "moving_sec": 777.0,
      "cum_sec": 5183.0
    },
    {
      "mile": 9,
      "split_sec": 659.6,
      "moving_sec": 659.6,
      "cum_sec": 5842.6
    },
    {
      "mile": 10,
      "split_sec": 1185.6,
      "moving_sec": 1185.6,
      "cum_sec": 7028.2
    },
    {
      "mile": 11,
      "split_sec": 679.4,
      "moving_sec": 679.4,
      "cum_sec": 7707.6
    },
    {
      "mile": 12,
      "split_sec": 816.5,
      "moving_sec": 816.5,
      "cum_sec": 8524.1
    },
    {
      "mile": 13,
      "split_sec": 718.4,
      "moving_sec": 718.4,
      "cum_sec": 9242.6
    },
    {
      "mile": 14,
      "split_sec": 887.9,
      "moving_sec": 887.9,
      "cum_sec": 10130.5
    },
    {
      "mile": 15,
      "split_sec": 980.0,
      "moving_sec": 980.0,
      "cum_sec": 11110.5
    },
    {
      "mile": 16,
      "split_sec": 1289.4,
      "moving_sec": 1289.4,
      "cum_sec": 12399.9
    },
    {
      "mile": 17,
      "split_sec": 829.8,
      "moving_sec": 829.8,
      "cum_sec": 13229.7
    },
    {
      "mile": 18,
      "split_sec": 2606.6,
      "moving_sec": 2606.6,
      "cum_sec": 15836.3
    },
    {
      "mile": 19,
      "split_sec": 787.5,
      "moving_sec": 787.5,
      "cum_sec": 16623.8
    },
    {
      "mile": 20,
      "split_sec": 973.7,
      "moving_sec": 973.7,
      "cum_sec": 17597.5
    },
    {
      "mile": 21,
      "split_sec": 944.9,
      "moving_sec": 944.9,
      "cum_sec": 18542.4
    },
    {
      "mile": 22,
      "split_sec": 950.6,
      "moving_sec": 950.6,
      "cum_sec": 19492.9
    },
    {
      "mile": 23,
      "split_sec": 977.7,
      "moving_sec": 977.7,
      "cum_sec": 20470.6
    },
    {
      "mile": 24,
      "split_sec": 610.8,
      "moving_sec": 610.8,
      "cum_sec": 21081.4
    }
  ]
}
