{
  "runner": "Wouter Baas",
  "gender": "M",
  "nationality": "NED",
  "year_of_birth": 1986,
  "race": "RUN Winschoten 100km",
  "year": 2022,
  "location": "Winschoten, Netherlands",
  "distance_id": "100k",
  "distance_km": 100,
  "distance_mi": 62.14,
  "duration_sec": 35281,
  "data_type": "checkpoints",
  "source": "DUV statistik.d-u-v.org",
  "checkpoints": [
    {
      "label": "50K",
      "cum_sec": 15251,
      "distance_km": 50,
      "distance_mi": 31.07
    },
    {
      "label": "50mi",
      "cum_sec": 28712,
      "distance_km": 80.47,
      "distance_mi": 50
    },
    {
      "label": "100K",
      "cum_sec": 35281,
      "distance_km": 100,
      "distance_mi": 62.14
    }
  ]
}